sqspy/__init__.py
sqspy/_base.py
sqspy/about.py
sqspy/consumer.py
sqspy/producer.py
sqspy-1.0.0.dist-info/METADATA
sqspy-1.0.0.dist-info/WHEEL
sqspy-1.0.0.dist-info/top_level.txt
sqspy-1.0.0.dist-info/RECORD
