Metadata-Version: 2.1
Name: sqspy
Version: 1.0.0
Summary: AWS SQS utility package for producing and consuming messages
Home-page: https://github.com/hjpotter92/sqspy
Author: hjpotter92
Author-email: sqspy@pypi.hjpotter92.email
License: MIT
Project-URL: Documentation, https://sqspy.rtfd.io/
Project-URL: Code coverage, https://app.codecov.io/gh/hjpotter92/sqspy
Project-URL: Builds history, https://travis-ci.com/hjpotter92/sqspy
Keywords: aws sqs messages producer consumer
Platform: any
Classifier: Development Status :: 4 - Beta
Classifier: Intended Audience :: Developers
Classifier: License :: OSI Approved :: MIT License
Classifier: Operating System :: OS Independent
Classifier: Programming Language :: Python :: 3
Classifier: Programming Language :: Python :: 3.6
Classifier: Programming Language :: Python :: 3.7
Classifier: Programming Language :: Python :: 3.8
Classifier: Programming Language :: Python :: 3.9
Classifier: Programming Language :: Python :: 3.10
Classifier: Programming Language :: Python :: 3 :: Only
Classifier: Programming Language :: Python :: Implementation
Classifier: Topic :: Software Development :: Libraries
Classifier: Topic :: Software Development :: Libraries :: Python Modules
Requires-Python: >=3.6
Requires-Dist: boto3 (>=1)
